gcodeparser/__init__.py
gcodeparser-0.3.0.dist-info/licenses/LICENSE
test/__init__.py
test/test_element_type.py
test/test_gcode_line.py
test/test_get_lines.py
test/test_parse_from_file.py
test/test_split_params.py
gcodeparser-0.3.0.dist-info/METADATA
gcodeparser-0.3.0.dist-info/WHEEL
gcodeparser-0.3.0.dist-info/top_level.txt
gcodeparser-0.3.0.dist-info/RECORD
